MANIFEST.in
PQPasswords
setup.cfg
setup.py
pqpasswords.egg-info/PKG-INFO
pqpasswords.egg-info/SOURCES.txt
pqpasswords.egg-info/dependency_links.txt
pqpasswords.egg-info/top_level.txt
pqpw/__init__.py
pqpw/config.py
pqpw/favicon.py
pqpw/loadframe.py
pqpw/recordframe.py
pqpw/settings.py
pqpw/utils.py
pqpw/vault.py
pqpw/vaultframe.py
pqpw/media/__init__.py
pqpw/twofish/__init__.py
pqpw/twofish/twofish.py
pqpw/twofish/twofish_cbc.py
pqpw/twofish/twofish_ecb.py
pqpw/widgets/__init__.py
pqpw/widgets/combo.py
pqpw/widgets/group.py
pqpw/widgets/record.py
pqpw/widgets/tree.py
share/applications/pqpw.desktop
share/icons/pqpw.svg
share/mime/packages/application-x-password-safe-v3.xml