Metadata-Version: 1.1
Name: pqpasswords
Version: 0.0.1
Summary: PWSafe3 compatible Password Manager
Home-page: https://sf.net/p/pqpasswords
Author: Okami
Author-email: okami@fuzetsu.info
License: GPLv3
Keywords: pqpasswords password safe
Platform: UNKNOWN
Classifier: Development Status :: 4 - Beta
Classifier: Environment :: Win32 (MS Windows)
Classifier: Environment :: X11 Applications :: Qt
Classifier: Intended Audience :: End Users/Desktop
Classifier: License :: OSI Approved :: GNU General Public License v3 or later (GPLv3+)
Classifier: Operating System :: OS Independent
Classifier: Programming Language :: Python :: 3 :: Only
Classifier: Topic :: Security :: Cryptography
